mkdocs_kuma_uptime_badge/__init__.py
mkdocs_kuma_uptime_badge/plugin.py
mkdocs_kuma_uptime_badge-0.1.0.dist-info/METADATA
mkdocs_kuma_uptime_badge-0.1.0.dist-info/WHEEL
mkdocs_kuma_uptime_badge-0.1.0.dist-info/entry_points.txt
mkdocs_kuma_uptime_badge-0.1.0.dist-info/RECORD
