Metadata-Version: 2.3
Name: mkdocs-kuma-uptime-badge
Version: 0.1.0
Summary: MkDocs plugin that converts shorthand placeholders to full Uptime Kuma badge links
License: MIT
Author: Jakub Dubec
Author-email: jdubec@culturepulse.ai
Requires-Python: >=3.10
Classifier: License :: OSI Approved :: MIT License
Classifier: Operating System :: OS Independent
Classifier: Programming Language :: Python :: 3
Classifier: Programming Language :: Python :: 3.10
Classifier: Programming Language :: Python :: 3.11
Classifier: Programming Language :: Python :: 3.12
Classifier: Programming Language :: Python :: 3.13
Classifier: Topic :: Documentation
Classifier: Topic :: Software Development :: Documentation
Requires-Dist: mkdocs (>=1.0.0)
